deepayan/__init__.py
deepayan/calculator.py
deepayan/file.py
deepayan/testing.py
deepayan-0.0.1.dist-info/LICENSE
deepayan-0.0.1.dist-info/METADATA
deepayan-0.0.1.dist-info/WHEEL
deepayan-0.0.1.dist-info/top_level.txt
deepayan-0.0.1.dist-info/RECORD
