Metadata-Version: 2.1
Name: deepayan
Version: 0.0.1
Summary: deepayan
Home-page: UNKNOWN
Author: Deepayan Thakur
Author-email: deepayankv8@gmail.com
License: UNKNOWN
Keywords: arithmetic,math,mathematics,python tutorial,deepayan thakur,Deepayan Thakur,file
Platform: UNKNOWN
Classifier: Development Status :: 1 - Planning
Classifier: Intended Audience :: Developers
Classifier: Programming Language :: Python :: 3
Classifier: Operating System :: Unix
Classifier: Operating System :: MacOS :: MacOS X
Classifier: Operating System :: Microsoft :: Windows
